[
    {
        "id": 105984160,
        "username": "edamamekun_"
    },
    {
        "id": 103375850,
        "username": "denkomaruKP"
    },
    {
        "id": 93690199,
        "username": "ww1ww"
    },
    {
        "id": 94556319,
        "username": "SPARKSNAKE"
    },
    {
        "id": 86631248,
        "username": "273796"
    },
    {
        "id": 78261776,
        "username": "8017326731"
    },
    {
        "id": 61299740,
        "username": "wataru_steak"
    },
    {
        "id": 83733943,
        "username": "tomokid"
    },
    {
        "id": 84794347,
        "username": "Bruhism"
    },
    {
        "id": 82539443,
        "username": "kage447"
    }
]